raodata/Data.py
raodata/File.py
raodata/Frame.py
raodata/FrameSet.py
raodata/SRHFits.py
raodata/SRHFolder.py
raodata/SRH_frames.py
raodata/__init__.py
raodata/exceptions.py
raodata/rot_xyz.py
tests/__init__.py
tests/test_data.py
tests/test_file.py
tests/test_srh_frames.py
tests/test_timeout.py
RAOdata-0.1.11.dist-info/LICENSE
RAOdata-0.1.11.dist-info/METADATA
RAOdata-0.1.11.dist-info/WHEEL
RAOdata-0.1.11.dist-info/top_level.txt
RAOdata-0.1.11.dist-info/RECORD
